<!DOCTYPE codename-engine-character>
<character x="0" icon="bf" y="350" isGF="false" flipX="true" isPlayer="true" gameOverChar="bf-holding-gf-dead" sprite="bf-holding-gf">
	<anim x="0" loop="false" y="0" fps="24" anim="BF idle dance" name="idle"/>
	<anim x="-29" loop="false" y="10" fps="24" anim="BF NOTE UP0" name="singUP"/>
	<anim x="-41" loop="false" y="23" fps="24" anim="BF NOTE LEFT0" name="singLEFT"/>
	<anim x="12" loop="false" y="7" fps="24" anim="BF NOTE RIGHT0" name="singRIGHT"/>
	<anim x="-10" loop="false" y="-10" fps="24" anim="BF NOTE DOWN0" name="singDOWN"/>
	<anim x="-29" loop="false" y="10" fps="24" anim="BF NOTE UP MISS" name="singUPmiss"/>
	<anim x="-41" loop="false" y="23" fps="24" anim="BF NOTE LEFT MISS" name="singLEFTmiss"/>
	<anim x="12" loop="false" y="7" fps="24" anim="BF NOTE RIGHT MISS" name="singRIGHTmiss"/>
	<anim x="-10" loop="false" y="-10" fps="24" anim="BF NOTE DOWN MISS" name="singDOWNmiss"/>
	<anim x="6" loop="false" y="88" fps="24" anim="BF catches GF" name="bfCatch"/>
</character>
